data_guard/__init__.py
data_guard/base_validator.py
data_guard/libs/__init__.py
data_guard/libs/helpers.py
data_guard/libs/rule_creator.py
data_guard/libs/rule_template.txt
data_guard/quick_validate.py
data_guard/rule.py
data_guard/rules/__init__.py
data_guard/rules/accepted.py
data_guard/rules/accepted_if.py
data_guard/rules/between.py
data_guard/rules/email.py
data_guard/rules/gt.py
data_guard/rules/gte.py
data_guard/rules/lt.py
data_guard/rules/lte.py
data_guard/rules/max.py
data_guard/rules/min.py
data_guard/rules/nullable.py
data_guard/rules/numeric.py
data_guard/rules/required.py
data_guard/rules/required_if.py
data_guard/rules/size.py
data_guard/rules/sometimes.py
data_guard/rules/string.py
data_guard/rules_mapper.py
data_guard/validation_response.py
data_guard/validator.py
data_guard-0.0.4.dist-info/LICENSE.md
data_guard-0.0.4.dist-info/METADATA
data_guard-0.0.4.dist-info/WHEEL
data_guard-0.0.4.dist-info/RECORD
