Metadata-Version: 2.1
Name: data-guard
Version: 0.0.4
Summary: Python data validation library
License: MIT
Author: Krunal Dodiya
Author-email: kunal.dodiya1@gmail.com
Requires-Python: >=3.10,<4.0
Classifier: License :: OSI Approved :: MIT License
Classifier: Programming Language :: Python :: 3
Classifier: Programming Language :: Python :: 3.10
Classifier: Programming Language :: Python :: 3.11
Classifier: Programming Language :: Python :: 3.12
Requires-Dist: colorama (>=0.4.6,<0.5.0)
Project-URL: documentation, https://data-guard.gitbook.io/docs
Project-URL: homepage, https://www.proalgotrader.com
Project-URL: repository, https://github.com/krunaldodiya/data-guard
